README.md
setup.py
py_counter/__init__.py
py_counter/py_counter.py
py_counter/setup.py
py_counter.egg-info/PKG-INFO
py_counter.egg-info/SOURCES.txt
py_counter.egg-info/dependency_links.txt
py_counter.egg-info/entry_points.txt
py_counter.egg-info/top_level.txt