Metadata-Version: 2.1
Name: py-counter
Version: 2.0
Summary: Python library that takes in a list/tuple and returns a hash map with an element:count of element in the list/tuple as a key:value pair
Home-page: https://github.com/shyams1993/py_counter
Author: SHYAM SALIL
Author-email: shyamsalil1993@gmail.com
License: MIT
Keywords: Powerful
Platform: UNKNOWN
Classifier: Development Status :: 4 - Beta
Classifier: Intended Audience :: Developers
Classifier: Topic :: Software Development :: Build Tools
Classifier: License :: OSI Approved :: MIT License
Classifier: Programming Language :: Python :: 3.4
Classifier: Programming Language :: Python :: 3.5
Classifier: Programming Language :: Python :: 3.6
Requires-Python: >=3.1
